odoo/addons/partner_identification_gln/README.rst
odoo/addons/partner_identification_gln/__init__.py
odoo/addons/partner_identification_gln/__manifest__.py
odoo/addons/partner_identification_gln/data/partner_identification_gln.xml
odoo/addons/partner_identification_gln/i18n/partner_identification_gln.pot
odoo/addons/partner_identification_gln/i18n/sl.po
odoo/addons/partner_identification_gln/models/__init__.py
odoo/addons/partner_identification_gln/models/res_partner_id_category.py
odoo/addons/partner_identification_gln/readme/CONTRIBUTORS.rst
odoo/addons/partner_identification_gln/readme/DESCRIPTION.rst
odoo/addons/partner_identification_gln/readme/INSTALL.rst
odoo/addons/partner_identification_gln/static/description/icon.svg
odoo/addons/partner_identification_gln/static/description/index.html
odoo/addons/partner_identification_gln/tests/__init__.py
odoo/addons/partner_identification_gln/tests/test_gln.py
odoo14_addon_partner_identification_gln-14.0.1.0.1.dist-info/METADATA
odoo14_addon_partner_identification_gln-14.0.1.0.1.dist-info/WHEEL
odoo14_addon_partner_identification_gln-14.0.1.0.1.dist-info/top_level.txt
odoo14_addon_partner_identification_gln-14.0.1.0.1.dist-info/RECORD
